ntrprtr/ByteInterpreter.py
ntrprtr/Controller.py
ntrprtr/__init__.py
ntrprtr/__main__.py
ntrprtr/action/ActionBase.py
ntrprtr/action/ActionType.py
ntrprtr/action/AsciiAction.py
ntrprtr/action/BinaryAction.py
ntrprtr/action/BitEqualsAction.py
ntrprtr/action/DOSDateAction.py
ntrprtr/action/DOSTimeAction.py
ntrprtr/action/DecimalAction.py
ntrprtr/action/EndianessAction.py
ntrprtr/action/EqualsAction.py
ntrprtr/action/ExtFileModeAction.py
ntrprtr/action/HexdumpAction.py
ntrprtr/action/UnicodeAction.py
ntrprtr/action/UnixTimeAction.py
ntrprtr/action/Win32TimeAction.py
ntrprtr/action/__init__.py
ntrprtr/printer/Printer.py
ntrprtr/printer/__init__.py
ntrprtr/util/TestFileCreator.py
ntrprtr/util/__init__.py
ntrprtr-2.3.1.dist-info/LICENSE.md
ntrprtr-2.3.1.dist-info/METADATA
ntrprtr-2.3.1.dist-info/WHEEL
ntrprtr-2.3.1.dist-info/entry_points.txt
ntrprtr-2.3.1.dist-info/top_level.txt
ntrprtr-2.3.1.dist-info/RECORD
