Metadata-Version: 2.1
Name: ntrprtr
Version: 2.3.1
Summary: Interpret bytes through different customizable actions
Home-page: https://github.com/5f0ne/ntrprtr
Author: 5f0
License: MIT
Classifier: Operating System :: OS Independent 
Classifier: Programming Language :: Python :: 3 
Classifier: License :: OSI Approved :: MIT License 
License-File: LICENSE.md
Requires-Dist: cnvrtr (==1.1.1)
Requires-Dist: hash-calc (==1.1.0)
